{"version": 0.6, "generator": "Overpass API 0.7.62.11 87bfad18", "osm3s": {"timestamp_osm_base": "2026-03-19T05:06:25Z", "copyright": "The data included in this document is from www.openstreetmap.org. The data is made available under ODbL."}, "elements": [{"type": "node", "id": 3238255124, "lat": 18.5164842, "lon": 73.8530314, "tags": {"amenity": "waste_disposal"}}, {"type": "node", "id": 11942749935, "lat": 18.4995695, "lon": 73.8487483, "tags": {"access": "yes", "amenity": "waste_disposal", "collection_times": "10.30 am to 12.30 pm", "waste": "mixed;organic;trash;plastic;glass"}}]}